qwentastic/__init__.py
qwentastic/core.py
qwentastic/example.py
qwentastic/setup.py
qwentastic-0.2.0.dist-info/METADATA
qwentastic-0.2.0.dist-info/WHEEL
qwentastic-0.2.0.dist-info/top_level.txt
qwentastic-0.2.0.dist-info/RECORD
