Metadata-Version: 2.2
Name: qwentastic
Version: 0.2.0
Summary: A simple interface for running various LLMs locally with function calling support
Author: Your Name
Author-email: Jacob Kuchinsky <jacob.kuchinsky@gmail.com>
License: MIT
Project-URL: Homepage, https://github.com/MrBanana124/qwentastic
Keywords: qwen,llama,deepseek,ai,language model,function calling
Classifier: Development Status :: 3 - Alpha
Classifier: Intended Audience :: Developers
Classifier: License :: OSI Approved :: MIT License
Classifier: Programming Language :: Python :: 3
Classifier: Programming Language :: Python :: 3.8
Classifier: Programming Language :: Python :: 3.9
Classifier: Programming Language :: Python :: 3.10
Requires-Python: >=3.8
Requires-Dist: torch>=2.0.0
Requires-Dist: transformers>=4.32.0
Requires-Dist: accelerate>=0.27.0
Requires-Dist: sentencepiece
Requires-Dist: protobuf
Dynamic: author
Dynamic: requires-python
